sentrysyslog/__init__.py
sentrysyslog/version.py
sentrysyslog/tests/__init__.py
sentrysyslog/tests/test_logging.py
sentrysyslog/tests/test_sentry.py
sentrysyslog/tests/test_sentrysyslog.py
sentry_syslog-0.1.5.dist-info/LICENSE
sentry_syslog-0.1.5.dist-info/METADATA
sentry_syslog-0.1.5.dist-info/WHEEL
sentry_syslog-0.1.5.dist-info/entry_points.txt
sentry_syslog-0.1.5.dist-info/top_level.txt
sentry_syslog-0.1.5.dist-info/RECORD
