Metadata-Version: 2.1
Name: sentry-syslog
Version: 0.1.5
Summary: Send syslog messages to Sentry as events
Home-page: https://github.com/rpatterson/sentry-syslog
Author: Ross Patterson
Author-email: me@rpatterson.net
License: UNKNOWN
Platform: UNKNOWN
Classifier: Programming Language :: Python :: 3
Classifier: License :: OSI Approved :: MIT License
Classifier: Operating System :: OS Independent
Requires-Python: >=3.6
Requires-Dist: syslog-rfc5424-parser
Requires-Dist: sentry-sdk
Provides-Extra: dev
Requires-Dist: pytest ; extra == 'dev'
Requires-Dist: pre-commit ; extra == 'dev'
Requires-Dist: coverage ; extra == 'dev'
Requires-Dist: flake8 ; extra == 'dev'
Requires-Dist: autoflake ; extra == 'dev'
Requires-Dist: autopep8 ; extra == 'dev'
Requires-Dist: flake8-black ; extra == 'dev'
